django_urlqueryset/__init__.py
django_urlqueryset/apps.py
django_urlqueryset/fields.py
django_urlqueryset/models.py
django_urlqueryset/settings.py
django_urlqueryset/storages.py
django_urlqueryset/urlqueryset.py
django_urlqueryset/utils.py
django_urlqueryset-0.9.0.dist-info/METADATA
django_urlqueryset-0.9.0.dist-info/WHEEL
django_urlqueryset-0.9.0.dist-info/top_level.txt
django_urlqueryset-0.9.0.dist-info/RECORD
