Metadata-Version: 2.1
Name: django-urlqueryset
Version: 0.9.0
Summary: UNKNOWN
Home-page: https://github.com/MaurizioPilia/django-urlqueryset
License: UNKNOWN
Platform: UNKNOWN
Requires-Dist: Django (>=2.2)
Requires-Dist: djangorestframework (>=3.9.4)
Requires-Dist: requests (>=2.11.1)
Requires-Dist: python-magic (>=0.4.18)
Provides-Extra: test
Requires-Dist: ipython ; extra == 'test'
Requires-Dist: ipdb ; extra == 'test'
Requires-Dist: Sphinx ; extra == 'test'
Requires-Dist: sphinx-rtd-theme ; extra == 'test'
